user_app/__init__.py
user_app/admin.py
user_app/apps.py
user_app/forms.py
user_app/models.py
user_app/settings.py
user_app/tests.py
user_app/utils.py
user_app/views.py
user_app/media/__init__.py
user_app/media/photo/anthony-emmanuel-1.jpg
user_app/migrations/0001_initial.py
user_app/migrations/0002_auto_20200319_1317.py
user_app/migrations/__init__.py
user_app/migrations/__pycache__/0001_initial.cpython-37.pyc
user_app/migrations/__pycache__/0002_auto_20200319_1317.cpython-37.pyc
user_app/migrations/__pycache__/__init__.cpython-37.pyc
user_app/static/__init__.py
user_app/static/user_app/allauth/style.css
user_app/templates/__init__.py
user_app/templates/base.html
user_app/templates/account/account_inactive.html
user_app/templates/account/base.html
user_app/templates/account/email.html
user_app/templates/account/email_confirm.html
user_app/templates/account/login.html
user_app/templates/account/logout.html
user_app/templates/account/password_change.html
user_app/templates/account/password_reset.html
user_app/templates/account/password_reset_done.html
user_app/templates/account/password_reset_from_key.html
user_app/templates/account/password_reset_from_key_done.html
user_app/templates/account/password_set.html
user_app/templates/account/signup.html
user_app/templates/account/signup_closed.html
user_app/templates/account/verification_sent.html
user_app/templates/account/verified_email_required.html
user_app/templates/account/email/email_confirmation_message.txt
user_app/templates/account/email/email_confirmation_signup_message.txt
user_app/templates/account/email/email_confirmation_signup_subject.txt
user_app/templates/account/email/email_confirmation_subject.txt
user_app/templates/account/email/password_reset_key_message.txt
user_app/templates/account/email/password_reset_key_subject.txt
user_app/templates/account/messages/cannot_delete_primary_email.txt
user_app/templates/account/messages/email_confirmation_sent.txt
Django_CustomUser_Model-1.1.0.dist-info/LICENSE
Django_CustomUser_Model-1.1.0.dist-info/METADATA
Django_CustomUser_Model-1.1.0.dist-info/WHEEL
Django_CustomUser_Model-1.1.0.dist-info/top_level.txt
Django_CustomUser_Model-1.1.0.dist-info/RECORD
