Metadata-Version: 2.1
Name: Django-CustomUser-Model
Version: 1.1.0
Summary: Django custom user model app and django allauth for authentication
Home-page: https://www.ghorz.com/blog/Apps/2020-03-20/21/django-custom-user-model-app-and-django-allauth/
Author: Anthony C. Emmanuel
Author-email: mymi14s@hotmail.com
License: UNKNOWN
Platform: UNKNOWN
Classifier: Programming Language :: Python :: 3
Classifier: License :: OSI Approved :: MIT License
Classifier: Operating System :: OS Independent
Requires-Dist: django-allauth
Requires-Dist: django-bootstrap4
